django_extended_makemessages/__init__.py
django_extended_makemessages/apps.py
django_extended_makemessages/management/commands/extendedmakemessages.py
django_extended_makemessages-1.7.0.dist-info/licenses/LICENSE
django_extended_makemessages-1.7.0.dist-info/METADATA
django_extended_makemessages-1.7.0.dist-info/WHEEL
django_extended_makemessages-1.7.0.dist-info/top_level.txt
django_extended_makemessages-1.7.0.dist-info/RECORD
