Metadata-Version: 2.4
Name: django-extended-makemessages
Version: 1.7.0
Summary: Extended version of Django's makemessages command that exposes selected GNU gettext tools options and adds new custom options, which further simplify message detection and translation files management.
Author: Michał Pokusa
Maintainer: Michał Pokusa
Project-URL: Repository, https://github.com/michalpokusa/django-extended-makemessages
Project-URL: Changelog, https://github.com/michalpokusa/django-extended-makemessages/blob/main/CHANGELOG.md
Keywords: django,extended,sort,sorted,messages,translations,makemessages,gettext,alias,fuzzy,untranslated,check,header,po,i18n,internationalization,localization,l10n,msgmerge,msguniq,msgattrib,xgettext
Classifier: Development Status :: 5 - Production/Stable
Classifier: Environment :: Console
Classifier: Framework :: Django :: 3.2
Classifier: Framework :: Django :: 4.0
Classifier: Framework :: Django :: 4.1
Classifier: Framework :: Django :: 4.2
Classifier: Framework :: Django :: 4
Classifier: Framework :: Django :: 5.0
Classifier: Framework :: Django :: 5.1
Classifier: Framework :: Django :: 5
Classifier: Intended Audience :: Developers
Classifier: Operating System :: OS Independent
Classifier: Programming Language :: Python :: 3 :: Only
Classifier: Programming Language :: Python :: 3.10
Classifier: Programming Language :: Python :: 3.11
Classifier: Programming Language :: Python :: 3.12
Classifier: Programming Language :: Python :: 3.6
Classifier: Programming Language :: Python :: 3.7
Classifier: Programming Language :: Python :: 3.8
Classifier: Programming Language :: Python :: 3.9
Classifier: Programming Language :: Python :: 3
Classifier: Programming Language :: Python
Classifier: Topic :: Software Development :: Internationalization
Classifier: Topic :: Software Development :: Libraries :: Python Modules
Classifier: Topic :: Software Development :: Localization
Classifier: Topic :: Utilities
License-File: LICENSE
Requires-Dist: django>=3.2
Dynamic: license-file
